odoo/addons/sale_report_delivered_elaboration/README.rst
odoo/addons/sale_report_delivered_elaboration/__init__.py
odoo/addons/sale_report_delivered_elaboration/__manifest__.py
odoo/addons/sale_report_delivered_elaboration/i18n/es.po
odoo/addons/sale_report_delivered_elaboration/i18n/sale_report_delivered_elaboration.pot
odoo/addons/sale_report_delivered_elaboration/readme/CONTRIBUTORS.rst
odoo/addons/sale_report_delivered_elaboration/readme/DESCRIPTION.rst
odoo/addons/sale_report_delivered_elaboration/readme/USAGE.rst
odoo/addons/sale_report_delivered_elaboration/reports/__init__.py
odoo/addons/sale_report_delivered_elaboration/reports/sale_report.py
odoo/addons/sale_report_delivered_elaboration/static/description/icon.png
odoo/addons/sale_report_delivered_elaboration/static/description/index.html
odoo13_addon_sale_report_delivered_elaboration-13.0.1.0.1.dev3.dist-info/METADATA
odoo13_addon_sale_report_delivered_elaboration-13.0.1.0.1.dev3.dist-info/WHEEL
odoo13_addon_sale_report_delivered_elaboration-13.0.1.0.1.dev3.dist-info/top_level.txt
odoo13_addon_sale_report_delivered_elaboration-13.0.1.0.1.dev3.dist-info/RECORD
